widgetastic_patternfly/__init__.py
widgetastic_patternfly/utils.py
widgetastic.patternfly-1.3.5.dist-info/LICENSE
widgetastic.patternfly-1.3.5.dist-info/METADATA
widgetastic.patternfly-1.3.5.dist-info/WHEEL
widgetastic.patternfly-1.3.5.dist-info/top_level.txt
widgetastic.patternfly-1.3.5.dist-info/RECORD
