Metadata-Version: 2.1
Name: widgetastic.patternfly
Version: 1.3.5
Summary: Patternfly widget library for Widgetastic
Home-page: https://github.com/RedHatQE/widgetastic.patternfly
Author: Milan Falesnik
Author-email: mfalesni@redhat.com
Maintainer: RedHatQE
Maintainer-email: mshriver@redhat.com
License: Apache license
Classifier: Programming Language :: Python
Classifier: Programming Language :: Python :: 3
Classifier: Programming Language :: Python :: 3.8
Classifier: Topic :: Software Development :: Libraries :: Python Modules
Classifier: Topic :: Software Development :: Quality Assurance
Classifier: Topic :: Software Development :: Testing
Requires-Python: >=3.8
License-File: LICENSE
Requires-Dist: widgetastic.core (>=1.0.0)
Provides-Extra: dev
Requires-Dist: podman ; extra == 'dev'
Requires-Dist: pre-commit ; extra == 'dev'
Requires-Dist: pytest ; extra == 'dev'
Requires-Dist: pytest-xdist ; extra == 'dev'
Requires-Dist: pytest-httpserver ; extra == 'dev'
Requires-Dist: pytest-cov ; extra == 'dev'
Provides-Extra: docs
Requires-Dist: sphinx ; extra == 'docs'
Provides-Extra: test
Requires-Dist: allure-pytest ; extra == 'test'
Requires-Dist: coveralls ; extra == 'test'
Requires-Dist: podman ; extra == 'test'
Requires-Dist: pytest ; extra == 'test'
Requires-Dist: pytest-httpserver ; extra == 'test'
Requires-Dist: pytest-cov ; extra == 'test'
Requires-Dist: pytest-xdist ; extra == 'test'
